[
    {
        "avgScore": 9677.142857142857,
        "coefNbLigneSupp": 102,
        "coefCasePerdu": 5,
        "coefCaseManquantes": 102,
        "coefHauteurRect": 50
    },
    {
        "avgScore": 9442.857142857143,
        "coefNbLigneSupp": 133,
        "coefCasePerdu": 12,
        "coefCaseManquantes": 73,
        "coefHauteurRect": 48
    },
    {
        "avgScore": 9331.42857142857,
        "coefNbLigneSupp": 83,
        "coefCasePerdu": 44,
        "coefCaseManquantes": 51,
        "coefHauteurRect": 54
    },
    {
        "avgScore": 7268.571428571428,
        "coefNbLigneSupp": 99,
        "coefCasePerdu": 17,
        "coefCaseManquantes": 81,
        "coefHauteurRect": 75
    },
    {
        "avgScore": 6585.714285714285,
        "coefNbLigneSupp": 74,
        "coefCasePerdu": 63,
        "coefCaseManquantes": 81,
        "coefHauteurRect": 70
    },
    {
        "avgScore": 5734.285714285715,
        "coefNbLigneSupp": 97,
        "coefCasePerdu": 62,
        "coefCaseManquantes": 94,
        "coefHauteurRect": 72
    },
    {
        "avgScore": 5137.142857142857,
        "coefNbLigneSupp": 114,
        "coefCasePerdu": 67,
        "coefCaseManquantes": 100,
        "coefHauteurRect": 95
    }
]