[
    {
        "avgScore": 6111.428571428572,
        "coefNbLigneSupp": 113,
        "coefCasePerdu": 26,
        "coefCaseManquantes": 114,
        "coefHauteurRect": 59
    },
    {
        "avgScore": 5477.142857142857,
        "coefNbLigneSupp": 113,
        "coefCasePerdu": 7,
        "coefCaseManquantes": 96,
        "coefHauteurRect": 49
    },
    {
        "avgScore": 5385.714285714285,
        "coefNbLigneSupp": 89,
        "coefCasePerdu": 23,
        "coefCaseManquantes": 100,
        "coefHauteurRect": 61
    },
    {
        "avgScore": 4580.0,
        "coefNbLigneSupp": 103,
        "coefCasePerdu": 13,
        "coefCaseManquantes": 108,
        "coefHauteurRect": 38
    },
    {
        "avgScore": 4360.0,
        "coefNbLigneSupp": 96,
        "coefCasePerdu": 13,
        "coefCaseManquantes": 115,
        "coefHauteurRect": 39
    },
    {
        "avgScore": 2091.4285714285716,
        "coefNbLigneSupp": 87,
        "coefCasePerdu": -1,
        "coefCaseManquantes": 107,
        "coefHauteurRect": 44
    },
    {
        "avgScore": 1522.857142857143,
        "coefNbLigneSupp": 95,
        "coefCasePerdu": -5,
        "coefCaseManquantes": 88,
        "coefHauteurRect": 43
    }
]